Metadata-Version: 2.1
Name: kahoot.py
Version: 1.0.0
Summary: A python package to interact with Kahoot!
Home-page: https://github.com/darthoce/kahoot.py
Author: DarthOCE
Author-email: darthocelogging@gmail.com
License: UNKNOWN
Keywords: kahoot,bot
Platform: UNKNOWN
Classifier: Programming Language :: Python :: 3
Classifier: License :: OSI Approved :: MIT License
Classifier: Operating System :: OS Independent
Requires-Python: >=3.6
